cdk_budibase/__init__.py
cdk_budibase/py.typed
cdk_budibase/_jsii/__init__.py
cdk_budibase/_jsii/cdk-budibase@0.0.816.jsii.tgz
cdk_budibase-0.0.816.dist-info/LICENSE
cdk_budibase-0.0.816.dist-info/METADATA
cdk_budibase-0.0.816.dist-info/WHEEL
cdk_budibase-0.0.816.dist-info/top_level.txt
cdk_budibase-0.0.816.dist-info/RECORD
