Metadata-Version: 2.1
Name: cdk-budibase
Version: 0.0.816
Summary: Use AWS CDK to create budibase server
Home-page: https://github.com/neilkuan/cdk-budibase.git
Author: Neil Kuan<guan840912@gmail.com>
License: Apache-2.0
Project-URL: Source, https://github.com/neilkuan/cdk-budibase.git
Classifier: Intended Audience :: Developers
Classifier: Operating System :: OS Independent
Classifier: Programming Language :: JavaScript
Classifier: Programming Language :: Python :: 3 :: Only
Classifier: Programming Language :: Python :: 3.9
Classifier: Programming Language :: Python :: 3.10
Classifier: Programming Language :: Python :: 3.11
Classifier: Typing :: Typed
Classifier: Development Status :: 4 - Beta
Classifier: License :: OSI Approved
Requires-Python: ~=3.9
License-File: LICENSE
Requires-Dist: aws-cdk-lib <3.0.0,>=2.63.0
Requires-Dist: constructs <11.0.0,>=10.0.5
Requires-Dist: jsii <2.0.0,>=1.119.0
Requires-Dist: publication >=0.0.3
Requires-Dist: typeguard <4.3.0,>=2.13.3
